AUTHORS
CHANGES
CONTRIBUTING
LICENSE
MANIFEST.in
README.rst
setup.py
tagcli.py
docs/.contributing.rst.swp
docs/.license.rst.swp
docs/.quickstart.rst.swp
docs/Makefile
docs/changes.rst
docs/conf.py
docs/contributing.rst
docs/index.rst
docs/installation.rst
docs/license.rst
docs/make.bat
docs/quickstart.rst
docs/usage.rst
tagcli.egg-info/PKG-INFO
tagcli.egg-info/SOURCES.txt
tagcli.egg-info/dependency_links.txt
tagcli.egg-info/entry_points.txt
tagcli.egg-info/not-zip-safe
tagcli.egg-info/requires.txt
tagcli.egg-info/top_level.txt
tests/.test_tagcli.py.swp
tests/__init__.py
tests/test_tagcli.py
tests/data/has-tags.m4a
tests/data/silence-44-s-v1.mp3