Metadata-Version: 1.0
Name: tagcli
Version: 0.2.0
Summary: A mutagen-based tag editor.
Home-page: https://github.com/kunxi/tagcli
Author: Kun Xi
Author-email: kunxi@kunxi.org
License: BSD
Keywords: tagcli
Platform: UNKNOWN
Classifier: Development Status :: 3 - Alpha
Classifier: Intended Audience :: Developers
Classifier: License :: OSI Approved :: BSD License
Classifier: Natural Language :: English
Classifier: Programming Language :: Python :: 2
Classifier: Programming Language :: Python :: 2.6
Classifier: Programming Language :: Python :: 2.7
